french_cities/__init__.py
french_cities/city_finder.py
french_cities/config.py
french_cities/constants.py
french_cities/departement_finder.py
french_cities/ultramarine_pseudo_cog.py
french_cities/utils.py
french_cities/vintage.py
french_cities-1.1.4.dist-info/LICENSE.md
french_cities-1.1.4.dist-info/METADATA
french_cities-1.1.4.dist-info/WHEEL
french_cities-1.1.4.dist-info/RECORD
