Metadata-Version: 2.3
Name: french-cities
Version: 1.1.4
Summary: Toolbox on french cities: set vintage, find departments, find cities...
License: GPL-3.0-or-later
Keywords: france,cities
Author: thomas.grandjean
Author-email: thomas.grandjean@developpement-durable.gouv.fr
Requires-Python: >=3.9,<4.0
Classifier: Development Status :: 5 - Production/Stable
Classifier: License :: OSI Approved :: GNU General Public License v3 or later (GPLv3+)
Classifier: Operating System :: OS Independent
Classifier: Programming Language :: Python :: 3
Classifier: Programming Language :: Python :: 3.9
Classifier: Programming Language :: Python :: 3.10
Classifier: Programming Language :: Python :: 3.11
Classifier: Programming Language :: Python :: 3.12
Classifier: Programming Language :: Python :: 3.13
Classifier: Topic :: Scientific/Engineering
Requires-Dist: diskcache (>=5.6.3,<6.0.0)
Requires-Dist: geopandas (>=1.0.1,<2.0.0)
Requires-Dist: geopy (>=2.3.0,<3.0.0)
Requires-Dist: importlib-metadata (>=6.8.0,<7.0.0)
Requires-Dist: pandas (>=2.2.2,<3.0.0)
Requires-Dist: pebble (>=5.0.3,<6.0.0)
Requires-Dist: platformdirs (>=4.2.2,<5.0.0)
Requires-Dist: pynsee (>=0.2.1,<0.3.0)
Requires-Dist: python-dotenv (>=1.0.0,<2.0.0)
Requires-Dist: rapidfuzz (>=3.1.1,<4.0.0)
Requires-Dist: requests-cache (>=1.2.1,<2.0.0)
Requires-Dist: setuptools (>=75.8.0,<76.0.0)
Requires-Dist: tqdm (>=4.65.0,<5.0.0)
Requires-Dist: unidecode (>=1.3.6,<2.0.0)
Project-URL: Bug Tracker, https://github.com/tgrandje/french-cities/issues
Project-URL: Documentation, https://tgrandje.github.io/french-cities/
Project-URL: Homepage, https://github.com/tgrandje/french-cities/
Project-URL: Repository, https://github.com/tgrandje/french-cities/
